hi_j25ng/__init__.py
hi_j25ng/hello.py
hi_j25ng-0.8.0.dist-info/METADATA
hi_j25ng-0.8.0.dist-info/WHEEL
hi_j25ng-0.8.0.dist-info/entry_points.txt
hi_j25ng-0.8.0.dist-info/top_level.txt
hi_j25ng-0.8.0.dist-info/RECORD
