Metadata-Version: 2.1
Name: hi_j25ng
Version: 0.8.0
Summary: Default template for PDM package
Author-email: j25ng <jsan2861@gmail.com>
License: MIT
Requires-Python: ==3.12.*
